README.rst
setup.py
mwm/__init__.py
mwm/mwm.py
mwm/mwmfile.py
mwm/mwmtool.py
mwm/osm2ft.py
mwm/types.txt
mwm.egg-info/PKG-INFO
mwm.egg-info/SOURCES.txt
mwm.egg-info/dependency_links.txt
mwm.egg-info/entry_points.txt
mwm.egg-info/top_level.txt