Metadata-Version: 1.1
Name: mwm
Version: 0.10.1
Summary: Library to read binary MAPS.ME files.
Home-page: https://github.com/mapsme/mwm.py
Author: Ilya Zverev
Author-email: ilya@zverev.info
License: Apache License 2.0
Platform: UNKNOWN
Classifier: Development Status :: 4 - Beta
Classifier: Intended Audience :: Developers
Classifier: Topic :: Software Development :: Libraries :: Python Modules
Classifier: Topic :: Utilities
Classifier: Environment :: Console
Classifier: License :: OSI Approved :: Apache Software License
Classifier: Programming Language :: Python
Classifier: Programming Language :: Python :: 2.7
Classifier: Programming Language :: Python :: 3
